{
  "jobs": [
    {
      "command": "0 3 * * * rails runner \"RefreshCommuneRecensementRatioJob.perform_async('all')\""
    },
    {
      "command": "0 * * * * rails runner SanityChecksJob.perform_async"
    },
    {
      "command": "0 8 * * * rails runner Campaigns::CronJob.perform_async"
    },
    {
      "command": "0 0 * * * rails runner Campaigns::SynchronizeOutdatedEmailsJob.perform_async"
    },
    {
      "command": "0 * * * * rails runner Campaigns::RefreshAllCampaignStatsJob.perform_async"
    }
  ]
}